<?xml version='1.0' encoding='utf8'?>
<hierarchy><android.widget.TextView bounds="[2258,144][3242,185]" class="android.widget.TextView" enabled="true" index="1" text="luct Industries Company Events Careers Contac" /><android.widget.TextView bounds="[2292,1079][2685,1110]" class="android.widget.TextView" enabled="true" index="1" text="technative.io | Sept 02, 2019" /><android.widget.TextView bounds="[1566,1524][2033,1560]" class="android.widget.TextView" enabled="true" index="1" text="Security Boulevard | Jun 20, 2019" /><android.widget.TextView bounds="[2316,980][2919,1019]" class="android.widget.TextView" enabled="true" index="1" text="vill Redefine Software Testing" /><android.widget.TextView bounds="[1569,999][1952,1029]" class="android.widget.TextView" enabled="true" index="1" text="techcentral.ie | Nov 8, 2019" /><android.widget.TextView bounds="[853,1426][1442,1472]" class="android.widget.TextView" enabled="true" index="1" text="Take Over Software Testing?" /><android.widget.TextView bounds="[839,1079][1242,1109]" class="android.widget.TextView" enabled="true" index="1" text="Business Post | Oct 10, 2020" /><android.widget.TextView bounds="[3375,148][3616,178]" class="android.widget.TextView" enabled="true" index="1" text="Request a Demo" /><android.widget.TextView bounds="[2301,1521][2828,1557]" class="android.widget.TextView" enabled="true" index="1" text="Search Quality Software | April 19, 2018" /><android.widget.TextView bounds="[2323,894][2924,943]" class="android.widget.TextView" enabled="true" index="1" text="Vhy AI and Machine Learning" /><android.widget.TextView bounds="[870,1346][1454,1392]" class="android.widget.TextView" enabled="true" index="1" text="Will AI and Machine Learning" /><android.widget.TextView bounds="[844,582][1555,650]" class="android.widget.TextView" enabled="true" index="1" text="Test.ai in the News" /><android.widget.TextView bounds="[852,984][1134,1019]" class="android.widget.TextView" enabled="true" index="1" text="use and value" /><android.widget.TextView bounds="[109,1638][2496,1672]" class="android.widget.TextView" enabled="true" index="1" text="sing this website, you agree to our use of cookies. We use cookies to provide you with a great experience and to help our website run effectively. Please review our privacy_policy for more information," /><android.widget.TextView bounds="[1574,1434][1760,1466]" class="android.widget.TextView" enabled="true" index="1" text="Podcasts" /><android.widget.TextView bounds="[884,1501][1485,1545]" class="android.widget.TextView" enabled="true" index="1" text="n Interview with Jason Arbor" /><android.widget.TextView bounds="[3144,149][3274,180]" class="android.widget.TextView" enabled="true" index="1" text="Contact" /><android.widget.TextView bounds="[2329,1434][2913,1466]" class="android.widget.TextView" enabled="true" index="1" text="rrived. Here's why robots rul" /><android.widget.TextView bounds="[2312,1342][2841,1393]" class="android.widget.TextView" enabled="true" index="1" text="AI in software testing has" /><android.widget.Image bounds="[216,117][580,199]" class="android.widget.Image" enabled="true" index="1" text="" /><android.widget.TextView bounds="[857,897][1410,933]" class="android.widget.TextView" enabled="true" index="1" text="Bridging the gap between F" /></hierarchy>