<?xml version='1.0' encoding='utf8'?>
<hierarchy><android.widget.TextView bounds="[2651,1307][2823,1336]" class="android.widget.TextView" enabled="true" index="1" text="deadlines" /><android.widget.TextView bounds="[512,249][1222,281]" class="android.widget.TextView" enabled="true" index="1" text="We Build Awesome AI-Powered Software Tesi" /><android.widget.TextView bounds="[1934,1145][2550,1183]" class="android.widget.TextView" enabled="true" index="1" text="AI-Bots scale testing to any platform," /><android.widget.TextView bounds="[1933,1212][2588,1244]" class="android.widget.TextView" enabled="true" index="1" text="any app. Create a test for one platform" /><android.widget.TextView bounds="[2657,571][2908,608]" class="android.widget.TextView" enabled="true" index="1" text="feature testing." /><android.widget.TextView bounds="[2645,504][3195,545]" class="android.widget.TextView" enabled="true" index="1" text="of DevOps. Never ship without full" /><android.widget.TextView bounds="[2660,451][3262,482]" class="android.widget.TextView" enabled="true" index="1" text="AI-Bots accelerate testing to the speec" /><android.widget.TextView bounds="[496,38][1354,101]" class="android.widget.TextView" enabled="true" index="1" text="Test.ai Helps Quality Assurance" /><android.widget.TextView bounds="[1941,522][2495,557]" class="android.widget.TextView" enabled="true" index="1" text="scripting. Anybody can do it... get" /><android.widget.TextView bounds="[2697,1245][3292,1280]" class="android.widget.TextView" enabled="true" index="1" text="sting running to meet critical business" /><android.widget.TextView bounds="[493,105][1026,163]" class="android.widget.TextView" enabled="true" index="1" text="Teams Outperform" /><android.widget.TextView bounds="[1938,582][2184,614]" class="android.widget.TextView" enabled="true" index="1" text="productive fast." /><android.widget.TextView bounds="[2650,1119][3268,1151]" class="android.widget.TextView" enabled="true" index="1" text="AI-Bots maintain tests automatically..." /><android.widget.TextView bounds="[1926,455][2537,490]" class="android.widget.TextView" enabled="true" index="1" text="AI-Bots build tests without coding or" /><android.widget.TextView bounds="[2659,304][2949,350]" class="android.widget.TextView" enabled="true" index="1" text="Accelerate" /><android.widget.TextView bounds="[1933,1267][2186,1290]" class="android.widget.TextView" enabled="true" index="1" text="denloy to many" /><android.widget.TextView bounds="[2680,41][2825,219]" class="android.widget.TextView" enabled="true" index="1" text="" /><android.widget.TextView bounds="[2664,977][2892,1024]" class="android.widget.TextView" enabled="true" index="1" text="Maintain" /><android.widget.TextView bounds="[2666,1301][2817,1322]" class="android.widget.TextView" enabled="true" index="1" text="Headlines" /><android.widget.TextView bounds="[2662,1186][3192,1216]" class="android.widget.TextView" enabled="true" index="1" text="mprove quality everywhere. Keep" /><android.widget.Image bounds="[1944,706][2150,899]" class="android.widget.Image" enabled="true" index="1" text="" /><android.widget.TextView bounds="[1935,1001][2091,1050]" class="android.widget.TextView" enabled="true" index="1" text="Scale" /><android.widget.TextView bounds="[1938,1276][2194,1302]" class="android.widget.TextView" enabled="true" index="1" text="deploy to many." /><android.widget.TextView bounds="[2687,701][2841,886]" class="android.widget.TextView" enabled="true" index="1" text="" /><android.widget.TextView bounds="[521,317][794,350]" class="android.widget.TextView" enabled="true" index="1" text="nutomation Tools" /></hierarchy>