{
    "action_info": {
        "elem_class": "screen", 
        "elem_info": {
            "class": "screen", 
            "hash": "X29XGJJk5pGlvIOUN0L1tA==\n", 
            "height": 1726, 
            "hier_level": 0, 
            "human_hash": "screen_X0_Y0_W3840_H1726", 
            "index": -1, 
            "is_transformed": true, 
            "tag_name": "screen", 
            "text": "", 
            "width": 3840, 
            "x": 0, 
            "y": 0
        }, 
        "gesture": "no_op", 
        "text": "no_op"
    }, 
    "all_elems": [
        {
            "behavior": "", 
            "checkable": false, 
            "class": "div", 
            "clickable": false, 
            "content-desc": "", 
            "enabled": false, 
            "focusable": false, 
            "focused": false, 
            "hash": "fZpZjpMBtzsEOQQJq/59qg==\n", 
            "height": 386, 
            "hier_level": 0, 
            "human_hash": "div_X1904_Y302_W716_H386", 
            "index": -1, 
            "internal": {
                "elem_dict": {
                    "attributes": {
                        "class": "sqs-block html-block sqs-block-html", 
                        "data-block-type": "2", 
                        "id": "block-yui_3_17_2_1_1605727448196_87082"
                    }, 
                    "background-color": "rgba(0, 0, 0, 0)", 
                    "class": "div", 
                    "color": "rgb(0, 0, 0)", 
                    "cssClass": "sqs-block html-block sqs-block-html", 
                    "domLevel": 13, 
                    "flags": {
                        "checkable": false, 
                        "clickable": false, 
                        "enabled": false, 
                        "focusable": false, 
                        "focused": false, 
                        "scrollable": false
                    }, 
                    "font-family": "ibm-plex-sans", 
                    "font-weight": "400", 
                    "fontSize": 17.6, 
                    "height": 193, 
                    "identifier": "block-yui_3_17_2_1_1605727448196_87082", 
                    "is-focused": false, 
                    "is-hidden": false, 
                    "name": "", 
                    "tagName": "div", 
                    "text": "BuildAI-Bots build tests without coding or scripting. Anybody can do it \u2026 get productive fast.", 
                    "type": "", 
                    "value": "", 
                    "width": 358, 
                    "x": 952, 
                    "xPercent": 49.998359580052494, 
                    "y": 151, 
                    "yPercent": 2.3476356077090457
                }, 
                "location": {
                    "x": 952, 
                    "y": 151
                }, 
                "size": {
                    "height": 193, 
                    "width": 358
                }, 
                "tag_name": "div", 
                "text": "BuildAI-Bots build tests without coding or scripting. Anybody can do it \u2026 get productive fast."
            }, 
            "is_transformed": true, 
            "package": "", 
            "password": false, 
            "resource-id": "", 
            "scrollable": false, 
            "tag_name": "div", 
            "text": "BuildAI-Bots build tests without coding or scripting. Anybody can do it \u2026 get productive fast.", 
            "transformed": true, 
            "width": 716, 
            "x": 1904, 
            "y": 302
        }, 
        {
            "behavior": "", 
            "checkable": false, 
            "class": "div", 
            "clickable": false, 
            "content-desc": "", 
            "enabled": false, 
            "focusable": false, 
            "focused": false, 
            "hash": "OUtvGNwMXa1Is9daBuBg4g==\n", 
            "height": 318, 
            "hier_level": 0, 
            "human_hash": "div_X2656_Y328_W650_H318", 
            "index": -1, 
            "internal": {
                "elem_dict": {
                    "attributes": {
                        "class": "sqs-block-content"
                    }, 
                    "background-color": "rgba(0, 0, 0, 0)", 
                    "class": "div", 
                    "color": "rgb(0, 0, 0)", 
                    "cssClass": "sqs-block-content", 
                    "domLevel": 12, 
                    "flags": {
                        "checkable": false, 
                        "clickable": false, 
                        "enabled": false, 
                        "focusable": false, 
                        "focused": false, 
                        "scrollable": false
                    }, 
                    "font-family": "ibm-plex-sans", 
                    "font-weight": "400", 
                    "fontSize": 17.6, 
                    "height": 159, 
                    "identifier": "", 
                    "is-focused": false, 
                    "is-hidden": false, 
                    "name": "", 
                    "tagName": "div", 
                    "text": "AccelerateAI-Bots accelerate testing to the speed of DevOps. Never ship without full feature testing.", 
                    "type": "", 
                    "value": "", 
                    "width": 325, 
                    "x": 1328, 
                    "xPercent": 69.71128608923884, 
                    "y": 164, 
                    "yPercent": 2.54507304942493
                }, 
                "location": {
                    "x": 1328, 
                    "y": 164
                }, 
                "size": {
                    "height": 159, 
                    "width": 325
                }, 
                "tag_name": "div", 
                "text": "AccelerateAI-Bots accelerate testing to the speed of DevOps. Never ship without full feature testing."
            }, 
            "is_transformed": true, 
            "package": "", 
            "password": false, 
            "resource-id": "", 
            "scrollable": false, 
            "tag_name": "div", 
            "text": "AccelerateAI-Bots accelerate testing to the speed of DevOps. Never ship without full feature testing.", 
            "transformed": true, 
            "width": 650, 
            "x": 2656, 
            "y": 328
        }, 
        {
            "behavior": "", 
            "checkable": false, 
            "class": "div", 
            "clickable": false, 
            "content-desc": "", 
            "enabled": false, 
            "focusable": false, 
            "focused": false, 
            "hash": "QzmS3LNtAy6kCGV2bnUMJw==\n", 
            "height": 380, 
            "hier_level": 0, 
            "human_hash": "div_X2656_Y998_W650_H380", 
            "index": -1, 
            "internal": {
                "elem_dict": {
                    "attributes": {
                        "class": "sqs-block-content"
                    }, 
                    "background-color": "rgba(0, 0, 0, 0)", 
                    "class": "div", 
                    "color": "rgb(0, 0, 0)", 
                    "cssClass": "sqs-block-content", 
                    "domLevel": 12, 
                    "flags": {
                        "checkable": false, 
                        "clickable": false, 
                        "enabled": false, 
                        "focusable": false, 
                        "focused": false, 
                        "scrollable": false
                    }, 
                    "font-family": "ibm-plex-sans", 
                    "font-weight": "400", 
                    "fontSize": 17.6, 
                    "height": 190, 
                    "identifier": "", 
                    "is-focused": false, 
                    "is-hidden": false, 
                    "name": "", 
                    "tagName": "div", 
                    "text": "MaintainAI-Bots maintain tests automatically... improve quality everywhere. Keep testing running to meet critical business deadlines", 
                    "type": "", 
                    "value": "", 
                    "width": 325, 
                    "x": 1328, 
                    "xPercent": 69.71128608923884, 
                    "y": 499, 
                    "yPercent": 7.749116024246192
                }, 
                "location": {
                    "x": 1328, 
                    "y": 499
                }, 
                "size": {
                    "height": 190, 
                    "width": 325
                }, 
                "tag_name": "div", 
                "text": "MaintainAI-Bots maintain tests automatically... improve quality everywhere. Keep testing running to meet critical business deadlines"
            }, 
            "is_transformed": true, 
            "package": "", 
            "password": false, 
            "resource-id": "", 
            "scrollable": false, 
            "tag_name": "div", 
            "text": "MaintainAI-Bots maintain tests automatically... improve quality everywhere. Keep testing running to meet critical business deadlines", 
            "transformed": true, 
            "width": 650, 
            "x": 2656, 
            "y": 998
        }, 
        {
            "behavior": "", 
            "checkable": false, 
            "class": "div", 
            "clickable": false, 
            "content-desc": "", 
            "enabled": false, 
            "focusable": false, 
            "focused": false, 
            "hash": "QSwUuzB66ePbb18hJqC5Bg==\n", 
            "height": 272, 
            "hier_level": 0, 
            "human_hash": "div_X1904_Y30_W716_H272", 
            "index": -1, 
            "internal": {
                "elem_dict": {
                    "attributes": {
                        "class": "sqs-block image-block sqs-block-image sqs-text-ready", 
                        "data-aspect-ratio": "31.48148148148148", 
                        "data-block-type": "5", 
                        "id": "block-yui_3_17_2_1_1605565453793_51805"
                    }, 
                    "background-color": "rgba(0, 0, 0, 0)", 
                    "class": "div", 
                    "color": "rgb(0, 0, 0)", 
                    "cssClass": "sqs-block image-block sqs-block-image sqs-text-ready", 
                    "domLevel": 13, 
                    "flags": {
                        "checkable": false, 
                        "clickable": false, 
                        "enabled": false, 
                        "focusable": false, 
                        "focused": false, 
                        "scrollable": false
                    }, 
                    "font-family": "ibm-plex-sans", 
                    "font-weight": "400", 
                    "fontSize": 17.6, 
                    "height": 136, 
                    "identifier": "block-yui_3_17_2_1_1605565453793_51805", 
                    "is-focused": false, 
                    "is-hidden": false, 
                    "name": "", 
                    "tagName": "div", 
                    "text": "<img src=\"https://images.squarespace-cdn.com/content/v1/5fa3332deadd8878ac4cb2cd/1605728212914-RAVUZAKQDFIMUR5GTWLN/ke17ZwdGBToddI8pDm48kOPtmt9kq3Df9ydK2LHH3aVZw-zPPgdn4jUwVcJE1ZvWQUxwkmyExglNqGp0IvTJZUJFbgE-7XRK3dMEBRBhUpxmGopNxzBDum4KUbtWB-MksiSdU5mjAVNjQAW-KQtSPhdWHkdEm-MnflhaMByAPFY/build.png\" alt=\"build.png\" />", 
                    "type": "", 
                    "value": "", 
                    "width": 358, 
                    "x": 952, 
                    "xPercent": 49.998359580052494, 
                    "y": 15, 
                    "yPercent": 0.23167935965184955
                }, 
                "location": {
                    "x": 952, 
                    "y": 15
                }, 
                "size": {
                    "height": 136, 
                    "width": 358
                }, 
                "tag_name": "div", 
                "text": "<img src=\"https://images.squarespace-cdn.com/content/v1/5fa3332deadd8878ac4cb2cd/1605728212914-RAVUZAKQDFIMUR5GTWLN/ke17ZwdGBToddI8pDm48kOPtmt9kq3Df9ydK2LHH3aVZw-zPPgdn4jUwVcJE1ZvWQUxwkmyExglNqGp0IvTJZUJFbgE-7XRK3dMEBRBhUpxmGopNxzBDum4KUbtWB-MksiSdU5mjAVNjQAW-KQtSPhdWHkdEm-MnflhaMByAPFY/build.png\" alt=\"build.png\" />"
            }, 
            "is_transformed": true, 
            "package": "", 
            "password": false, 
            "resource-id": "", 
            "scrollable": false, 
            "tag_name": "div", 
            "text": "<img src=\"https://images.squarespace-cdn.com/content/v1/5fa3332deadd8878ac4cb2cd/1605728212914-RAVUZAKQDFIMUR5GTWLN/ke17ZwdGBToddI8pDm48kOPtmt9kq3Df9ydK2LHH3aVZw-zPPgdn4jUwVcJE1ZvWQUxwkmyExglNqGp0IvTJZUJFbgE-7XRK3dMEBRBhUpxmGopNxzBDum4KUbtWB-MksiSdU5mjAVNjQAW-KQtSPhdWHkdEm-MnflhaMByAPFY/build.png\" alt=\"build.png\" />", 
            "transformed": true, 
            "width": 716, 
            "x": 1904, 
            "y": 30
        }, 
        {
            "behavior": "", 
            "checkable": false, 
            "class": "div", 
            "clickable": false, 
            "content-desc": "", 
            "enabled": false, 
            "focusable": false, 
            "focused": false, 
            "hash": "AATP6AStEhLJUVHe3LH68A==\n", 
            "height": 216, 
            "hier_level": 0, 
            "human_hash": "div_X2656_Y714_W650_H216", 
            "index": -1, 
            "internal": {
                "elem_dict": {
                    "attributes": {
                        "class": "image-block-wrapper has-aspect-ratio preSlide slideIn", 
                        "data-animation-role": "image", 
                        "id": "yui_3_17_2_1_1611600788843_253", 
                        "style": "padding-bottom: 33.2308%; overflow: hidden; transition-timing-function: ease; transition-duration: 0.8s; transition-delay: 0.241237s;"
                    }, 
                    "background-color": "rgba(0, 0, 0, 0)", 
                    "class": "div", 
                    "color": "rgb(0, 0, 0)", 
                    "cssClass": "image-block-wrapper has-aspect-ratio preSlide slideIn", 
                    "domLevel": 15, 
                    "flags": {
                        "checkable": false, 
                        "clickable": false, 
                        "enabled": false, 
                        "focusable": false, 
                        "focused": false, 
                        "scrollable": false
                    }, 
                    "font-family": "ibm-plex-sans", 
                    "font-weight": "400", 
                    "fontSize": 17.6, 
                    "height": 108, 
                    "identifier": "yui_3_17_2_1_1611600788843_253", 
                    "is-focused": false, 
                    "is-hidden": false, 
                    "name": "", 
                    "tagName": "div", 
                    "text": "<img src=\"https://images.squarespace-cdn.com/content/v1/5fa3332deadd8878ac4cb2cd/1605728350719-6J9X0ZBFEFYMJE1QH9TB/ke17ZwdGBToddI8pDm48kOPtmt9kq3Df9ydK2LHH3aVZw-zPPgdn4jUwVcJE1ZvWQUxwkmyExglNqGp0IvTJZUJFbgE-7XRK3dMEBRBhUpxmGopNxzBDum4KUbtWB-MksiSdU5mjAVNjQAW-KQtSPhdWHkdEm-MnflhaMByAPFY/maintain.png\" alt=\"maintain.png\" />", 
                    "type": "", 
                    "value": "", 
                    "width": 325, 
                    "x": 1328, 
                    "xPercent": 69.71128608923884, 
                    "y": 357, 
                    "yPercent": 5.544762200808206
                }, 
                "location": {
                    "x": 1328, 
                    "y": 357
                }, 
                "size": {
                    "height": 108, 
                    "width": 325
                }, 
                "tag_name": "div", 
                "text": "<img src=\"https://images.squarespace-cdn.com/content/v1/5fa3332deadd8878ac4cb2cd/1605728350719-6J9X0ZBFEFYMJE1QH9TB/ke17ZwdGBToddI8pDm48kOPtmt9kq3Df9ydK2LHH3aVZw-zPPgdn4jUwVcJE1ZvWQUxwkmyExglNqGp0IvTJZUJFbgE-7XRK3dMEBRBhUpxmGopNxzBDum4KUbtWB-MksiSdU5mjAVNjQAW-KQtSPhdWHkdEm-MnflhaMByAPFY/maintain.png\" alt=\"maintain.png\" />"
            }, 
            "is_transformed": true, 
            "package": "", 
            "password": false, 
            "resource-id": "", 
            "scrollable": false, 
            "tag_name": "div", 
            "text": "<img src=\"https://images.squarespace-cdn.com/content/v1/5fa3332deadd8878ac4cb2cd/1605728350719-6J9X0ZBFEFYMJE1QH9TB/ke17ZwdGBToddI8pDm48kOPtmt9kq3Df9ydK2LHH3aVZw-zPPgdn4jUwVcJE1ZvWQUxwkmyExglNqGp0IvTJZUJFbgE-7XRK3dMEBRBhUpxmGopNxzBDum4KUbtWB-MksiSdU5mjAVNjQAW-KQtSPhdWHkdEm-MnflhaMByAPFY/maintain.png\" alt=\"maintain.png\" />", 
            "transformed": true, 
            "width": 650, 
            "x": 2656, 
            "y": 714
        }, 
        {
            "behavior": "", 
            "checkable": false, 
            "class": "div", 
            "clickable": false, 
            "content-desc": "", 
            "enabled": false, 
            "focusable": false, 
            "focused": false, 
            "hash": "f7KUlBDZ7nzjCvyzMMDy7g==\n", 
            "height": 524, 
            "hier_level": 0, 
            "human_hash": "div_X472_Y30_W956_H524", 
            "index": -1, 
            "internal": {
                "elem_dict": {
                    "attributes": {
                        "class": "col sqs-col-4 span-4"
                    }, 
                    "background-color": "rgba(0, 0, 0, 0)", 
                    "class": "div", 
                    "color": "rgb(0, 0, 0)", 
                    "cssClass": "col sqs-col-4 span-4", 
                    "domLevel": 12, 
                    "flags": {
                        "checkable": false, 
                        "clickable": false, 
                        "enabled": false, 
                        "focusable": false, 
                        "focused": false, 
                        "scrollable": false
                    }, 
                    "font-family": "ibm-plex-sans", 
                    "font-weight": "400", 
                    "fontSize": 17.6, 
                    "height": 262, 
                    "identifier": "", 
                    "is-focused": false, 
                    "is-hidden": false, 
                    "name": "", 
                    "tagName": "div", 
                    "text": "Test.ai Helps Quality Assurance Teams Outperform  We Build Awesome AI-Powered Software Test Automation Tools", 
                    "type": "", 
                    "value": "", 
                    "width": 478, 
                    "x": 236, 
                    "xPercent": 12.36220472440945, 
                    "y": 15, 
                    "yPercent": 0.23167935965184955
                }, 
                "location": {
                    "x": 236, 
                    "y": 15
                }, 
                "size": {
                    "height": 262, 
                    "width": 478
                }, 
                "tag_name": "div", 
                "text": "Test.ai Helps Quality Assurance Teams Outperform  We Build Awesome AI-Powered Software Test Automation Tools"
            }, 
            "is_transformed": true, 
            "package": "", 
            "password": false, 
            "resource-id": "", 
            "scrollable": false, 
            "tag_name": "div", 
            "text": "Test.ai Helps Quality Assurance Teams Outperform  We Build Awesome AI-Powered Software Test Automation Tools", 
            "transformed": true, 
            "width": 956, 
            "x": 472, 
            "y": 30
        }, 
        {
            "behavior": "", 
            "checkable": false, 
            "class": "div", 
            "clickable": false, 
            "content-desc": "", 
            "enabled": false, 
            "focusable": false, 
            "focused": false, 
            "hash": "TPFgBw8x6EdgVU7RkWLqfg==\n", 
            "height": 386, 
            "hier_level": 0, 
            "human_hash": "div_X1904_Y988_W716_H386", 
            "index": -1, 
            "internal": {
                "elem_dict": {
                    "attributes": {
                        "class": "sqs-block html-block sqs-block-html", 
                        "data-block-type": "2", 
                        "id": "block-33d6de863ec7c1286c12"
                    }, 
                    "background-color": "rgba(0, 0, 0, 0)", 
                    "class": "div", 
                    "color": "rgb(0, 0, 0)", 
                    "cssClass": "sqs-block html-block sqs-block-html", 
                    "domLevel": 13, 
                    "flags": {
                        "checkable": false, 
                        "clickable": false, 
                        "enabled": false, 
                        "focusable": false, 
                        "focused": false, 
                        "scrollable": false
                    }, 
                    "font-family": "ibm-plex-sans", 
                    "font-weight": "400", 
                    "fontSize": 17.6, 
                    "height": 193, 
                    "identifier": "block-33d6de863ec7c1286c12", 
                    "is-focused": false, 
                    "is-hidden": false, 
                    "name": "", 
                    "tagName": "div", 
                    "text": "ScaleAI-Bots scale testing to any platform, any app. Create a test for one platform - deploy to many.", 
                    "type": "", 
                    "value": "", 
                    "width": 358, 
                    "x": 952, 
                    "xPercent": 49.998359580052494, 
                    "y": 494, 
                    "yPercent": 7.676746580665215
                }, 
                "location": {
                    "x": 952, 
                    "y": 494
                }, 
                "size": {
                    "height": 193, 
                    "width": 358
                }, 
                "tag_name": "div", 
                "text": "ScaleAI-Bots scale testing to any platform, any app. Create a test for one platform - deploy to many."
            }, 
            "is_transformed": true, 
            "package": "", 
            "password": false, 
            "resource-id": "", 
            "scrollable": false, 
            "tag_name": "div", 
            "text": "ScaleAI-Bots scale testing to any platform, any app. Create a test for one platform - deploy to many.", 
            "transformed": true, 
            "width": 716, 
            "x": 1904, 
            "y": 988
        }, 
        {
            "behavior": "", 
            "checkable": false, 
            "class": "div", 
            "clickable": false, 
            "content-desc": "", 
            "enabled": false, 
            "focusable": false, 
            "focused": false, 
            "hash": "v2Rcm7wkxcRbUp7ktHYXlQ==\n", 
            "height": 284, 
            "hier_level": 0, 
            "human_hash": "div_X2622_Y680_W718_H284", 
            "index": -1, 
            "internal": {
                "elem_dict": {
                    "attributes": {
                        "class": "sqs-block image-block sqs-block-image sqs-text-ready", 
                        "data-aspect-ratio": "33.23076923076923", 
                        "data-block-type": "5", 
                        "id": "block-yui_3_17_2_1_1605635471495_376778"
                    }, 
                    "background-color": "rgba(0, 0, 0, 0)", 
                    "class": "div", 
                    "color": "rgb(0, 0, 0)", 
                    "cssClass": "sqs-block image-block sqs-block-image sqs-text-ready", 
                    "domLevel": 11, 
                    "flags": {
                        "checkable": false, 
                        "clickable": false, 
                        "enabled": false, 
                        "focusable": false, 
                        "focused": false, 
                        "scrollable": false
                    }, 
                    "font-family": "ibm-plex-sans", 
                    "font-weight": "400", 
                    "fontSize": 17.6, 
                    "height": 142, 
                    "identifier": "block-yui_3_17_2_1_1605635471495_376778", 
                    "is-focused": false, 
                    "is-hidden": false, 
                    "name": "", 
                    "tagName": "div", 
                    "text": "<img src=\"https://images.squarespace-cdn.com/content/v1/5fa3332deadd8878ac4cb2cd/1605728350719-6J9X0ZBFEFYMJE1QH9TB/ke17ZwdGBToddI8pDm48kOPtmt9kq3Df9ydK2LHH3aVZw-zPPgdn4jUwVcJE1ZvWQUxwkmyExglNqGp0IvTJZUJFbgE-7XRK3dMEBRBhUpxmGopNxzBDum4KUbtWB-MksiSdU5mjAVNjQAW-KQtSPhdWHkdEm-MnflhaMByAPFY/maintain.png\" alt=\"maintain.png\" />", 
                    "type": "", 
                    "value": "", 
                    "width": 359, 
                    "x": 1311, 
                    "xPercent": 68.81889763779527, 
                    "y": 340, 
                    "yPercent": 5.280540876593099
                }, 
                "location": {
                    "x": 1311, 
                    "y": 340
                }, 
                "size": {
                    "height": 142, 
                    "width": 359
                }, 
                "tag_name": "div", 
                "text": "<img src=\"https://images.squarespace-cdn.com/content/v1/5fa3332deadd8878ac4cb2cd/1605728350719-6J9X0ZBFEFYMJE1QH9TB/ke17ZwdGBToddI8pDm48kOPtmt9kq3Df9ydK2LHH3aVZw-zPPgdn4jUwVcJE1ZvWQUxwkmyExglNqGp0IvTJZUJFbgE-7XRK3dMEBRBhUpxmGopNxzBDum4KUbtWB-MksiSdU5mjAVNjQAW-KQtSPhdWHkdEm-MnflhaMByAPFY/maintain.png\" alt=\"maintain.png\" />"
            }, 
            "is_transformed": true, 
            "package": "", 
            "password": false, 
            "resource-id": "", 
            "scrollable": false, 
            "tag_name": "div", 
            "text": "<img src=\"https://images.squarespace-cdn.com/content/v1/5fa3332deadd8878ac4cb2cd/1605728350719-6J9X0ZBFEFYMJE1QH9TB/ke17ZwdGBToddI8pDm48kOPtmt9kq3Df9ydK2LHH3aVZw-zPPgdn4jUwVcJE1ZvWQUxwkmyExglNqGp0IvTJZUJFbgE-7XRK3dMEBRBhUpxmGopNxzBDum4KUbtWB-MksiSdU5mjAVNjQAW-KQtSPhdWHkdEm-MnflhaMByAPFY/maintain.png\" alt=\"maintain.png\" />", 
            "transformed": true, 
            "width": 718, 
            "x": 2622, 
            "y": 680
        }, 
        {
            "behavior": "", 
            "checkable": false, 
            "class": "div", 
            "clickable": false, 
            "content-desc": "", 
            "enabled": false, 
            "focusable": false, 
            "focused": false, 
            "hash": "ejETwy5xIRJFrAUGNdVGUg==\n", 
            "height": 136, 
            "hier_level": 0, 
            "human_hash": "div_X1426_Y30_W478_H136", 
            "index": -1, 
            "internal": {
                "elem_dict": {
                    "attributes": {
                        "class": "col sqs-col-2 span-2"
                    }, 
                    "background-color": "rgba(0, 0, 0, 0)", 
                    "class": "div", 
                    "color": "rgb(0, 0, 0)", 
                    "cssClass": "col sqs-col-2 span-2", 
                    "domLevel": 12, 
                    "flags": {
                        "checkable": false, 
                        "clickable": false, 
                        "enabled": false, 
                        "focusable": false, 
                        "focused": false, 
                        "scrollable": false
                    }, 
                    "font-family": "ibm-plex-sans", 
                    "font-weight": "400", 
                    "fontSize": 17.6, 
                    "height": 68, 
                    "identifier": "", 
                    "is-focused": false, 
                    "is-hidden": false, 
                    "name": "", 
                    "tagName": "div", 
                    "text": "", 
                    "type": "", 
                    "value": "", 
                    "width": 239, 
                    "x": 713, 
                    "xPercent": 37.45324803149606, 
                    "y": 15, 
                    "yPercent": 0.23167935965184955
                }, 
                "location": {
                    "x": 713, 
                    "y": 15
                }, 
                "size": {
                    "height": 68, 
                    "width": 239
                }, 
                "tag_name": "div", 
                "text": ""
            }, 
            "is_transformed": true, 
            "package": "", 
            "password": false, 
            "resource-id": "", 
            "scrollable": false, 
            "tag_name": "div", 
            "text": "", 
            "transformed": true, 
            "width": 478, 
            "x": 1426, 
            "y": 30
        }, 
        {
            "behavior": "", 
            "checkable": false, 
            "class": "div", 
            "clickable": false, 
            "content-desc": "", 
            "enabled": false, 
            "focusable": false, 
            "focused": false, 
            "hash": "7Jf3PgG6SBHuzihm+f+pIA==\n", 
            "height": 1382, 
            "hier_level": 0, 
            "human_hash": "div_X2622_Y30_W718_H1382", 
            "index": -1, 
            "internal": {
                "elem_dict": {
                    "attributes": {
                        "class": "col sqs-col-3 span-3", 
                        "id": "yui_3_17_2_1_1611600788843_239"
                    }, 
                    "background-color": "rgba(0, 0, 0, 0)", 
                    "class": "div", 
                    "color": "rgb(0, 0, 0)", 
                    "cssClass": "col sqs-col-3 span-3", 
                    "domLevel": 10, 
                    "flags": {
                        "checkable": false, 
                        "clickable": false, 
                        "enabled": false, 
                        "focusable": false, 
                        "focused": false, 
                        "scrollable": false
                    }, 
                    "font-family": "ibm-plex-sans", 
                    "font-weight": "400", 
                    "fontSize": 17.6, 
                    "height": 691, 
                    "identifier": "yui_3_17_2_1_1611600788843_239", 
                    "is-focused": false, 
                    "is-hidden": false, 
                    "name": "", 
                    "tagName": "div", 
                    "text": "<img src=\"https://images.squarespace-cdn.com/content/v1/5fa3332deadd8878ac4cb2cd/1605728167723-UBWELOTLNHQGW3HC4X02/ke17ZwdGBToddI8pDm48kOPtmt9kq3Df9ydK2LHH3aVZw-zPPgdn4jUwVcJE1ZvWQUxwkmyExglNqGp0IvTJZUJFbgE-7XRK3dMEBRBhUpxmGopNxzBDum4KUbtWB-MksiSdU5mjAVNjQAW-KQtSPhdWHkdEm-MnflhaMByAPFY/accelerate.png\" alt=\"accelerate.png\" />\n          \n        \n          \n        \n\n        \n      \n        \n      \n\n    \n  \n\n\n  \n\n\nAccelerateAI-Bots accelerate testing to the speed of DevOps. Never ship without full feature testing.\n\n\n\n\n\n\n\n\n  \n\n    \n  \n    \n\n      \n\n      \n        \n          \n        \n        \n\n        \n          \n            \n          \n            <img src=\"https://images.squarespace-cdn.com/content/v1/5fa3332deadd8878ac4cb2cd/1605728350719-6J9X0ZBFEFYMJE1QH9TB/ke17ZwdGBToddI8pDm48kOPtmt9kq3Df9ydK2LHH3aVZw-zPPgdn4jUwVcJE1ZvWQUxwkmyExglNqGp0IvTJZUJFbgE-7XRK3dMEBRBhUpxmGopNxzBDum4KUbtWB-MksiSdU5mjAVNjQAW-KQtSPhdWHkdEm-MnflhaMByAPFY/maintain.png\" alt=\"maintain.png\" />\n          \n        \n          \n        \n\n        \n      \n        \n      \n\n    \n  \n\n\n  \n\n\nMaintainAI-Bots maintain tests automatically... improve quality everywhere. Keep testing running to meet critical business deadlines", 
                    "type": "", 
                    "value": "", 
                    "width": 359, 
                    "x": 1311, 
                    "xPercent": 68.81889763779527, 
                    "y": 15, 
                    "yPercent": 0.23167935965184955
                }, 
                "location": {
                    "x": 1311, 
                    "y": 15
                }, 
                "size": {
                    "height": 691, 
                    "width": 359
                }, 
                "tag_name": "div", 
                "text": "<img src=\"https://images.squarespace-cdn.com/content/v1/5fa3332deadd8878ac4cb2cd/1605728167723-UBWELOTLNHQGW3HC4X02/ke17ZwdGBToddI8pDm48kOPtmt9kq3Df9ydK2LHH3aVZw-zPPgdn4jUwVcJE1ZvWQUxwkmyExglNqGp0IvTJZUJFbgE-7XRK3dMEBRBhUpxmGopNxzBDum4KUbtWB-MksiSdU5mjAVNjQAW-KQtSPhdWHkdEm-MnflhaMByAPFY/accelerate.png\" alt=\"accelerate.png\" />\n          \n        \n          \n        \n\n        \n      \n        \n      \n\n    \n  \n\n\n  \n\n\nAccelerateAI-Bots accelerate testing to the speed of DevOps. Never ship without full feature testing.\n\n\n\n\n\n\n\n\n  \n\n    \n  \n    \n\n      \n\n      \n        \n          \n        \n        \n\n        \n          \n            \n          \n            <img src=\"https://images.squarespace-cdn.com/content/v1/5fa3332deadd8878ac4cb2cd/1605728350719-6J9X0ZBFEFYMJE1QH9TB/ke17ZwdGBToddI8pDm48kOPtmt9kq3Df9ydK2LHH3aVZw-zPPgdn4jUwVcJE1ZvWQUxwkmyExglNqGp0IvTJZUJFbgE-7XRK3dMEBRBhUpxmGopNxzBDum4KUbtWB-MksiSdU5mjAVNjQAW-KQtSPhdWHkdEm-MnflhaMByAPFY/maintain.png\" alt=\"maintain.png\" />\n          \n        \n          \n        \n\n        \n      \n        \n      \n\n    \n  \n\n\n  \n\n\nMaintainAI-Bots maintain tests automatically... improve quality everywhere. Keep testing running to meet critical business deadlines"
            }, 
            "is_transformed": true, 
            "package": "", 
            "password": false, 
            "resource-id": "", 
            "scrollable": false, 
            "tag_name": "div", 
            "text": "<img src=\"https://images.squarespace-cdn.com/content/v1/5fa3332deadd8878ac4cb2cd/1605728167723-UBWELOTLNHQGW3HC4X02/ke17ZwdGBToddI8pDm48kOPtmt9kq3Df9ydK2LHH3aVZw-zPPgdn4jUwVcJE1ZvWQUxwkmyExglNqGp0IvTJZUJFbgE-7XRK3dMEBRBhUpxmGopNxzBDum4KUbtWB-MksiSdU5mjAVNjQAW-KQtSPhdWHkdEm-MnflhaMByAPFY/accelerate.png\" alt=\"accelerate.png\" />\n          \n        \n          \n        \n\n        \n      \n        \n      \n\n    \n  \n\n\n  \n\n\nAccelerateAI-Bots accelerate testing to the speed of DevOps. Never ship without full feature testing.\n\n\n\n\n\n\n\n\n  \n\n    \n  \n    \n\n      \n\n      \n        \n          \n        \n        \n\n        \n          \n            \n          \n            <img src=\"https://images.squarespace-cdn.com/content/v1/5fa3332deadd8878ac4cb2cd/1605728350719-6J9X0ZBFEFYMJE1QH9TB/ke17ZwdGBToddI8pDm48kOPtmt9kq3Df9ydK2LHH3aVZw-zPPgdn4jUwVcJE1ZvWQUxwkmyExglNqGp0IvTJZUJFbgE-7XRK3dMEBRBhUpxmGopNxzBDum4KUbtWB-MksiSdU5mjAVNjQAW-KQtSPhdWHkdEm-MnflhaMByAPFY/maintain.png\" alt=\"maintain.png\" />\n          \n        \n          \n        \n\n        \n      \n        \n      \n\n    \n  \n\n\n  \n\n\nMaintainAI-Bots maintain tests automatically... improve quality everywhere. Keep testing running to meet critical business deadlines", 
            "transformed": true, 
            "width": 718, 
            "x": 2622, 
            "y": 30
        }, 
        {
            "behavior": "", 
            "checkable": false, 
            "class": "div", 
            "clickable": false, 
            "content-desc": "", 
            "enabled": false, 
            "focusable": false, 
            "focused": false, 
            "hash": "VxLCmWVVBrfQYK9ADejiLw==\n", 
            "height": 386, 
            "hier_level": 0, 
            "human_hash": "div_X2622_Y294_W718_H386", 
            "index": -1, 
            "internal": {
                "elem_dict": {
                    "attributes": {
                        "class": "sqs-block html-block sqs-block-html", 
                        "data-block-type": "2", 
                        "id": "block-5c6f44c37c8f29a21b5e"
                    }, 
                    "background-color": "rgba(0, 0, 0, 0)", 
                    "class": "div", 
                    "color": "rgb(0, 0, 0)", 
                    "cssClass": "sqs-block html-block sqs-block-html", 
                    "domLevel": 11, 
                    "flags": {
                        "checkable": false, 
                        "clickable": false, 
                        "enabled": false, 
                        "focusable": false, 
                        "focused": false, 
                        "scrollable": false
                    }, 
                    "font-family": "ibm-plex-sans", 
                    "font-weight": "400", 
                    "fontSize": 17.6, 
                    "height": 193, 
                    "identifier": "block-5c6f44c37c8f29a21b5e", 
                    "is-focused": false, 
                    "is-hidden": false, 
                    "name": "", 
                    "tagName": "div", 
                    "text": "AccelerateAI-Bots accelerate testing to the speed of DevOps. Never ship without full feature testing.", 
                    "type": "", 
                    "value": "", 
                    "width": 359, 
                    "x": 1311, 
                    "xPercent": 68.81889763779527, 
                    "y": 147, 
                    "yPercent": 2.2808517252098226
                }, 
                "location": {
                    "x": 1311, 
                    "y": 147
                }, 
                "size": {
                    "height": 193, 
                    "width": 359
                }, 
                "tag_name": "div", 
                "text": "AccelerateAI-Bots accelerate testing to the speed of DevOps. Never ship without full feature testing."
            }, 
            "is_transformed": true, 
            "package": "", 
            "password": false, 
            "resource-id": "", 
            "scrollable": false, 
            "tag_name": "div", 
            "text": "AccelerateAI-Bots accelerate testing to the speed of DevOps. Never ship without full feature testing.", 
            "transformed": true, 
            "width": 718, 
            "x": 2622, 
            "y": 294
        }, 
        {
            "behavior": "", 
            "checkable": false, 
            "class": "div", 
            "clickable": false, 
            "content-desc": "", 
            "enabled": false, 
            "focusable": false, 
            "focused": false, 
            "hash": "Srw66ZhSMyDCICae65s59w==\n", 
            "height": 300, 
            "hier_level": 0, 
            "human_hash": "div_X1904_Y688_W716_H300", 
            "index": -1, 
            "internal": {
                "elem_dict": {
                    "attributes": {
                        "class": "sqs-block image-block sqs-block-image sqs-text-ready", 
                        "data-block-type": "5", 
                        "id": "block-yui_3_17_2_1_1605635471495_308958"
                    }, 
                    "background-color": "rgba(0, 0, 0, 0)", 
                    "class": "div", 
                    "color": "rgb(0, 0, 0)", 
                    "cssClass": "sqs-block image-block sqs-block-image sqs-text-ready", 
                    "domLevel": 13, 
                    "flags": {
                        "checkable": false, 
                        "clickable": false, 
                        "enabled": false, 
                        "focusable": false, 
                        "focused": false, 
                        "scrollable": false
                    }, 
                    "font-family": "ibm-plex-sans", 
                    "font-weight": "400", 
                    "fontSize": 17.6, 
                    "height": 150, 
                    "identifier": "block-yui_3_17_2_1_1605635471495_308958", 
                    "is-focused": false, 
                    "is-hidden": false, 
                    "name": "", 
                    "tagName": "div", 
                    "text": "<img src=\"https://images.squarespace-cdn.com/content/v1/5fa3332deadd8878ac4cb2cd/1605728189125-ROASF0VGWL1FDL4AR1GN/ke17ZwdGBToddI8pDm48kOPtmt9kq3Df9ydK2LHH3aVZw-zPPgdn4jUwVcJE1ZvWQUxwkmyExglNqGp0IvTJZUJFbgE-7XRK3dMEBRBhUpxmGopNxzBDum4KUbtWB-MksiSdU5mjAVNjQAW-KQtSPhdWHkdEm-MnflhaMByAPFY/scale.png\" alt=\"scale.png\" />", 
                    "type": "", 
                    "value": "", 
                    "width": 358, 
                    "x": 952, 
                    "xPercent": 49.998359580052494, 
                    "y": 344, 
                    "yPercent": 5.347324759092322
                }, 
                "location": {
                    "x": 952, 
                    "y": 344
                }, 
                "size": {
                    "height": 150, 
                    "width": 358
                }, 
                "tag_name": "div", 
                "text": "<img src=\"https://images.squarespace-cdn.com/content/v1/5fa3332deadd8878ac4cb2cd/1605728189125-ROASF0VGWL1FDL4AR1GN/ke17ZwdGBToddI8pDm48kOPtmt9kq3Df9ydK2LHH3aVZw-zPPgdn4jUwVcJE1ZvWQUxwkmyExglNqGp0IvTJZUJFbgE-7XRK3dMEBRBhUpxmGopNxzBDum4KUbtWB-MksiSdU5mjAVNjQAW-KQtSPhdWHkdEm-MnflhaMByAPFY/scale.png\" alt=\"scale.png\" />"
            }, 
            "is_transformed": true, 
            "package": "", 
            "password": false, 
            "resource-id": "", 
            "scrollable": false, 
            "tag_name": "div", 
            "text": "<img src=\"https://images.squarespace-cdn.com/content/v1/5fa3332deadd8878ac4cb2cd/1605728189125-ROASF0VGWL1FDL4AR1GN/ke17ZwdGBToddI8pDm48kOPtmt9kq3Df9ydK2LHH3aVZw-zPPgdn4jUwVcJE1ZvWQUxwkmyExglNqGp0IvTJZUJFbgE-7XRK3dMEBRBhUpxmGopNxzBDum4KUbtWB-MksiSdU5mjAVNjQAW-KQtSPhdWHkdEm-MnflhaMByAPFY/scale.png\" alt=\"scale.png\" />", 
            "transformed": true, 
            "width": 716, 
            "x": 1904, 
            "y": 688
        }, 
        {
            "behavior": "", 
            "checkable": false, 
            "class": "div", 
            "clickable": false, 
            "content-desc": "", 
            "enabled": false, 
            "focusable": false, 
            "focused": false, 
            "hash": "Bx5AzNvTrCgC8bgzMSQcuA==\n", 
            "height": 196, 
            "hier_level": 0, 
            "human_hash": "div_X2656_Y64_W650_H196", 
            "index": -1, 
            "internal": {
                "elem_dict": {
                    "attributes": {
                        "class": "image-block-wrapper has-aspect-ratio preSlide slideIn", 
                        "data-animation-role": "image", 
                        "id": "yui_3_17_2_1_1611600788843_235", 
                        "style": "padding-bottom: 30.1538%; overflow: hidden; transition-timing-function: ease; transition-duration: 0.8s; transition-delay: 0.22268s;"
                    }, 
                    "background-color": "rgba(0, 0, 0, 0)", 
                    "class": "div", 
                    "color": "rgb(0, 0, 0)", 
                    "cssClass": "image-block-wrapper has-aspect-ratio preSlide slideIn", 
                    "domLevel": 15, 
                    "flags": {
                        "checkable": false, 
                        "clickable": false, 
                        "enabled": false, 
                        "focusable": false, 
                        "focused": false, 
                        "scrollable": false
                    }, 
                    "font-family": "ibm-plex-sans", 
                    "font-weight": "400", 
                    "fontSize": 17.6, 
                    "height": 98, 
                    "identifier": "yui_3_17_2_1_1611600788843_235", 
                    "is-focused": false, 
                    "is-hidden": false, 
                    "name": "", 
                    "tagName": "div", 
                    "text": "<img src=\"https://images.squarespace-cdn.com/content/v1/5fa3332deadd8878ac4cb2cd/1605728167723-UBWELOTLNHQGW3HC4X02/ke17ZwdGBToddI8pDm48kOPtmt9kq3Df9ydK2LHH3aVZw-zPPgdn4jUwVcJE1ZvWQUxwkmyExglNqGp0IvTJZUJFbgE-7XRK3dMEBRBhUpxmGopNxzBDum4KUbtWB-MksiSdU5mjAVNjQAW-KQtSPhdWHkdEm-MnflhaMByAPFY/accelerate.png\" alt=\"accelerate.png\" />", 
                    "type": "", 
                    "value": "", 
                    "width": 325, 
                    "x": 1328, 
                    "xPercent": 69.71128608923884, 
                    "y": 32, 
                    "yPercent": 0.4959006838669568
                }, 
                "location": {
                    "x": 1328, 
                    "y": 32
                }, 
                "size": {
                    "height": 98, 
                    "width": 325
                }, 
                "tag_name": "div", 
                "text": "<img src=\"https://images.squarespace-cdn.com/content/v1/5fa3332deadd8878ac4cb2cd/1605728167723-UBWELOTLNHQGW3HC4X02/ke17ZwdGBToddI8pDm48kOPtmt9kq3Df9ydK2LHH3aVZw-zPPgdn4jUwVcJE1ZvWQUxwkmyExglNqGp0IvTJZUJFbgE-7XRK3dMEBRBhUpxmGopNxzBDum4KUbtWB-MksiSdU5mjAVNjQAW-KQtSPhdWHkdEm-MnflhaMByAPFY/accelerate.png\" alt=\"accelerate.png\" />"
            }, 
            "is_transformed": true, 
            "package": "", 
            "password": false, 
            "resource-id": "", 
            "scrollable": false, 
            "tag_name": "div", 
            "text": "<img src=\"https://images.squarespace-cdn.com/content/v1/5fa3332deadd8878ac4cb2cd/1605728167723-UBWELOTLNHQGW3HC4X02/ke17ZwdGBToddI8pDm48kOPtmt9kq3Df9ydK2LHH3aVZw-zPPgdn4jUwVcJE1ZvWQUxwkmyExglNqGp0IvTJZUJFbgE-7XRK3dMEBRBhUpxmGopNxzBDum4KUbtWB-MksiSdU5mjAVNjQAW-KQtSPhdWHkdEm-MnflhaMByAPFY/accelerate.png\" alt=\"accelerate.png\" />", 
            "transformed": true, 
            "width": 650, 
            "x": 2656, 
            "y": 64
        }, 
        {
            "behavior": "", 
            "checkable": false, 
            "class": "div", 
            "clickable": false, 
            "content-desc": "", 
            "enabled": false, 
            "focusable": false, 
            "focused": false, 
            "hash": "/eXjZbORKsVkmXwYrIgJDw==\n", 
            "height": 456, 
            "hier_level": 0, 
            "human_hash": "div_X506_Y64_W888_H456", 
            "index": -1, 
            "internal": {
                "elem_dict": {
                    "attributes": {
                        "class": "sqs-block-content"
                    }, 
                    "background-color": "rgba(0, 0, 0, 0)", 
                    "class": "div", 
                    "color": "rgb(0, 0, 0)", 
                    "cssClass": "sqs-block-content", 
                    "domLevel": 14, 
                    "flags": {
                        "checkable": false, 
                        "clickable": false, 
                        "enabled": false, 
                        "focusable": false, 
                        "focused": false, 
                        "scrollable": false
                    }, 
                    "font-family": "ibm-plex-sans", 
                    "font-weight": "400", 
                    "fontSize": 17.6, 
                    "height": 228, 
                    "identifier": "", 
                    "is-focused": false, 
                    "is-hidden": false, 
                    "name": "", 
                    "tagName": "div", 
                    "text": "Test.ai Helps Quality Assurance Teams Outperform  We Build Awesome AI-Powered Software Test Automation Tools", 
                    "type": "", 
                    "value": "", 
                    "width": 444, 
                    "x": 253, 
                    "xPercent": 13.254593175853019, 
                    "y": 32, 
                    "yPercent": 0.4959006838669568
                }, 
                "location": {
                    "x": 253, 
                    "y": 32
                }, 
                "size": {
                    "height": 228, 
                    "width": 444
                }, 
                "tag_name": "div", 
                "text": "Test.ai Helps Quality Assurance Teams Outperform  We Build Awesome AI-Powered Software Test Automation Tools"
            }, 
            "is_transformed": true, 
            "package": "", 
            "password": false, 
            "resource-id": "", 
            "scrollable": false, 
            "tag_name": "div", 
            "text": "Test.ai Helps Quality Assurance Teams Outperform  We Build Awesome AI-Powered Software Test Automation Tools", 
            "transformed": true, 
            "width": 888, 
            "x": 506, 
            "y": 64
        }, 
        {
            "behavior": "", 
            "checkable": false, 
            "class": "div", 
            "clickable": false, 
            "content-desc": "", 
            "enabled": false, 
            "focusable": false, 
            "focused": false, 
            "hash": "Uw574VriBgQZje2ygCo+yA==\n", 
            "height": 318, 
            "hier_level": 0, 
            "human_hash": "div_X1938_Y1022_W648_H318", 
            "index": -1, 
            "internal": {
                "elem_dict": {
                    "attributes": {
                        "class": "sqs-block-content"
                    }, 
                    "background-color": "rgba(0, 0, 0, 0)", 
                    "class": "div", 
                    "color": "rgb(0, 0, 0)", 
                    "cssClass": "sqs-block-content", 
                    "domLevel": 14, 
                    "flags": {
                        "checkable": false, 
                        "clickable": false, 
                        "enabled": false, 
                        "focusable": false, 
                        "focused": false, 
                        "scrollable": false
                    }, 
                    "font-family": "ibm-plex-sans", 
                    "font-weight": "400", 
                    "fontSize": 17.6, 
                    "height": 159, 
                    "identifier": "", 
                    "is-focused": false, 
                    "is-hidden": false, 
                    "name": "", 
                    "tagName": "div", 
                    "text": "ScaleAI-Bots scale testing to any platform, any app. Create a test for one platform - deploy to many.", 
                    "type": "", 
                    "value": "", 
                    "width": 324, 
                    "x": 969, 
                    "xPercent": 50.89074803149606, 
                    "y": 511, 
                    "yPercent": 7.940967904880323
                }, 
                "location": {
                    "x": 969, 
                    "y": 511
                }, 
                "size": {
                    "height": 159, 
                    "width": 324
                }, 
                "tag_name": "div", 
                "text": "ScaleAI-Bots scale testing to any platform, any app. Create a test for one platform - deploy to many."
            }, 
            "is_transformed": true, 
            "package": "", 
            "password": false, 
            "resource-id": "", 
            "scrollable": false, 
            "tag_name": "div", 
            "text": "ScaleAI-Bots scale testing to any platform, any app. Create a test for one platform - deploy to many.", 
            "transformed": true, 
            "width": 648, 
            "x": 1938, 
            "y": 1022
        }, 
        {
            "behavior": "", 
            "checkable": false, 
            "class": "div", 
            "clickable": false, 
            "content-desc": "", 
            "enabled": false, 
            "focusable": false, 
            "focused": false, 
            "hash": "S2lZEVLOeVX5/XnhWRCUTA==\n", 
            "height": 318, 
            "hier_level": 0, 
            "human_hash": "div_X1938_Y336_W648_H318", 
            "index": -1, 
            "internal": {
                "elem_dict": {
                    "attributes": {
                        "class": "sqs-block-content"
                    }, 
                    "background-color": "rgba(0, 0, 0, 0)", 
                    "class": "div", 
                    "color": "rgb(0, 0, 0)", 
                    "cssClass": "sqs-block-content", 
                    "domLevel": 14, 
                    "flags": {
                        "checkable": false, 
                        "clickable": false, 
                        "enabled": false, 
                        "focusable": false, 
                        "focused": false, 
                        "scrollable": false
                    }, 
                    "font-family": "ibm-plex-sans", 
                    "font-weight": "400", 
                    "fontSize": 17.6, 
                    "height": 159, 
                    "identifier": "", 
                    "is-focused": false, 
                    "is-hidden": false, 
                    "name": "", 
                    "tagName": "div", 
                    "text": "BuildAI-Bots build tests without coding or scripting. Anybody can do it \u2026 get productive fast.", 
                    "type": "", 
                    "value": "", 
                    "width": 324, 
                    "x": 969, 
                    "xPercent": 50.89074803149606, 
                    "y": 168, 
                    "yPercent": 2.611856931924153
                }, 
                "location": {
                    "x": 969, 
                    "y": 168
                }, 
                "size": {
                    "height": 159, 
                    "width": 324
                }, 
                "tag_name": "div", 
                "text": "BuildAI-Bots build tests without coding or scripting. Anybody can do it \u2026 get productive fast."
            }, 
            "is_transformed": true, 
            "package": "", 
            "password": false, 
            "resource-id": "", 
            "scrollable": false, 
            "tag_name": "div", 
            "text": "BuildAI-Bots build tests without coding or scripting. Anybody can do it \u2026 get productive fast.", 
            "transformed": true, 
            "width": 648, 
            "x": 1938, 
            "y": 336
        }, 
        {
            "behavior": "", 
            "checkable": false, 
            "class": "h3", 
            "clickable": false, 
            "content-desc": "", 
            "enabled": false, 
            "focusable": false, 
            "focused": false, 
            "hash": "uV9KNZ+Ok4jXtg4TjzVr1A==\n", 
            "height": 92, 
            "hier_level": 0, 
            "human_hash": "h3_X506_Y1630_W2800_H92", 
            "index": -1, 
            "internal": {
                "elem_dict": {
                    "attributes": {
                        "class": "preSlide slideIn", 
                        "style": "text-align: center; white-space: pre-wrap; transition-timing-function: ease; transition-duration: 0.8s; transition-delay: 0.259794s;"
                    }, 
                    "background-color": "rgba(0, 0, 0, 0)", 
                    "class": "h3", 
                    "color": "rgb(255, 255, 255)", 
                    "cssClass": "preSlide slideIn", 
                    "domLevel": 13, 
                    "flags": {
                        "checkable": false, 
                        "clickable": false, 
                        "enabled": false, 
                        "focusable": false, 
                        "focused": false, 
                        "scrollable": false
                    }, 
                    "font-family": "Montserrat", 
                    "font-weight": "700", 
                    "fontSize": 35.2, 
                    "height": 46, 
                    "identifier": "", 
                    "is-focused": false, 
                    "is-hidden": false, 
                    "name": "", 
                    "tagName": "h3", 
                    "text": "Benefits for Your Team", 
                    "type": "", 
                    "value": "", 
                    "width": 1400, 
                    "x": 253, 
                    "xPercent": 13.254593175853019, 
                    "y": 815, 
                    "yPercent": 12.66732398197078
                }, 
                "location": {
                    "x": 253, 
                    "y": 815
                }, 
                "size": {
                    "height": 46, 
                    "width": 1400
                }, 
                "tag_name": "h3", 
                "text": "Benefits for Your Team"
            }, 
            "is_transformed": true, 
            "package": "", 
            "password": false, 
            "resource-id": "", 
            "scrollable": false, 
            "tag_name": "h3", 
            "text": "Benefits for Your Team", 
            "transformed": true, 
            "width": 2800, 
            "x": 506, 
            "y": 1630
        }, 
        {
            "behavior": "", 
            "checkable": false, 
            "class": "div", 
            "clickable": false, 
            "content-desc": "", 
            "enabled": false, 
            "focusable": false, 
            "focused": false, 
            "hash": "PB+KE3/AnKAufxBn50vb3A==\n", 
            "height": 264, 
            "hier_level": 0, 
            "human_hash": "div_X2622_Y30_W718_H264", 
            "index": -1, 
            "internal": {
                "elem_dict": {
                    "attributes": {
                        "class": "sqs-block image-block sqs-block-image sqs-text-ready", 
                        "data-aspect-ratio": "30.153846153846153", 
                        "data-block-type": "5", 
                        "id": "block-yui_3_17_2_1_1605635471495_364671"
                    }, 
                    "background-color": "rgba(0, 0, 0, 0)", 
                    "class": "div", 
                    "color": "rgb(0, 0, 0)", 
                    "cssClass": "sqs-block image-block sqs-block-image sqs-text-ready", 
                    "domLevel": 11, 
                    "flags": {
                        "checkable": false, 
                        "clickable": false, 
                        "enabled": false, 
                        "focusable": false, 
                        "focused": false, 
                        "scrollable": false
                    }, 
                    "font-family": "ibm-plex-sans", 
                    "font-weight": "400", 
                    "fontSize": 17.6, 
                    "height": 132, 
                    "identifier": "block-yui_3_17_2_1_1605635471495_364671", 
                    "is-focused": false, 
                    "is-hidden": false, 
                    "name": "", 
                    "tagName": "div", 
                    "text": "<img src=\"https://images.squarespace-cdn.com/content/v1/5fa3332deadd8878ac4cb2cd/1605728167723-UBWELOTLNHQGW3HC4X02/ke17ZwdGBToddI8pDm48kOPtmt9kq3Df9ydK2LHH3aVZw-zPPgdn4jUwVcJE1ZvWQUxwkmyExglNqGp0IvTJZUJFbgE-7XRK3dMEBRBhUpxmGopNxzBDum4KUbtWB-MksiSdU5mjAVNjQAW-KQtSPhdWHkdEm-MnflhaMByAPFY/accelerate.png\" alt=\"accelerate.png\" />", 
                    "type": "", 
                    "value": "", 
                    "width": 359, 
                    "x": 1311, 
                    "xPercent": 68.81889763779527, 
                    "y": 15, 
                    "yPercent": 0.23167935965184955
                }, 
                "location": {
                    "x": 1311, 
                    "y": 15
                }, 
                "size": {
                    "height": 132, 
                    "width": 359
                }, 
                "tag_name": "div", 
                "text": "<img src=\"https://images.squarespace-cdn.com/content/v1/5fa3332deadd8878ac4cb2cd/1605728167723-UBWELOTLNHQGW3HC4X02/ke17ZwdGBToddI8pDm48kOPtmt9kq3Df9ydK2LHH3aVZw-zPPgdn4jUwVcJE1ZvWQUxwkmyExglNqGp0IvTJZUJFbgE-7XRK3dMEBRBhUpxmGopNxzBDum4KUbtWB-MksiSdU5mjAVNjQAW-KQtSPhdWHkdEm-MnflhaMByAPFY/accelerate.png\" alt=\"accelerate.png\" />"
            }, 
            "is_transformed": true, 
            "package": "", 
            "password": false, 
            "resource-id": "", 
            "scrollable": false, 
            "tag_name": "div", 
            "text": "<img src=\"https://images.squarespace-cdn.com/content/v1/5fa3332deadd8878ac4cb2cd/1605728167723-UBWELOTLNHQGW3HC4X02/ke17ZwdGBToddI8pDm48kOPtmt9kq3Df9ydK2LHH3aVZw-zPPgdn4jUwVcJE1ZvWQUxwkmyExglNqGp0IvTJZUJFbgE-7XRK3dMEBRBhUpxmGopNxzBDum4KUbtWB-MksiSdU5mjAVNjQAW-KQtSPhdWHkdEm-MnflhaMByAPFY/accelerate.png\" alt=\"accelerate.png\" />", 
            "transformed": true, 
            "width": 718, 
            "x": 2622, 
            "y": 30
        }, 
        {
            "behavior": "", 
            "checkable": false, 
            "class": "a", 
            "clickable": true, 
            "content-desc": "", 
            "enabled": false, 
            "focusable": true, 
            "focused": false, 
            "hash": "fTAm9a48M3Z2rnQhCr5nTg==\n", 
            "height": 112, 
            "hier_level": 0, 
            "human_hash": "a_X506_Y270_W724_H112", 
            "index": -1, 
            "internal": {
                "elem_dict": {
                    "attributes": {
                        "href": "/all-products"
                    }, 
                    "background-color": "rgba(0, 0, 0, 0)", 
                    "class": "a", 
                    "color": "rgb(43, 38, 197)", 
                    "domLevel": 16, 
                    "flags": {
                        "checkable": false, 
                        "clickable": true, 
                        "enabled": false, 
                        "focusable": true, 
                        "focused": false, 
                        "scrollable": false
                    }, 
                    "font-family": "ibm-plex-sans", 
                    "font-weight": "400", 
                    "fontSize": 17.6, 
                    "height": 56, 
                    "identifier": "", 
                    "is-focused": false, 
                    "is-hidden": false, 
                    "name": "", 
                    "tagName": "a", 
                    "text": "We Build Awesome AI-Powered Software Test Automation Tools", 
                    "type": "", 
                    "value": "", 
                    "width": 362, 
                    "x": 253, 
                    "xPercent": 13.254593175853019, 
                    "y": 135, 
                    "yPercent": 2.0967710599937828
                }, 
                "location": {
                    "x": 253, 
                    "y": 135
                }, 
                "size": {
                    "height": 56, 
                    "width": 362
                }, 
                "tag_name": "a", 
                "text": "We Build Awesome AI-Powered Software Test Automation Tools"
            }, 
            "is_transformed": true, 
            "package": "", 
            "password": false, 
            "resource-id": "", 
            "scrollable": false, 
            "tag_name": "a", 
            "text": "We Build Awesome AI-Powered Software Test Automation Tools", 
            "transformed": true, 
            "width": 724, 
            "x": 506, 
            "y": 270
        }, 
        {
            "behavior": "", 
            "checkable": false, 
            "class": "div", 
            "clickable": false, 
            "content-desc": "", 
            "enabled": false, 
            "focusable": false, 
            "focused": false, 
            "hash": "A+Ewl06juUFRoB9n3rmmOw==\n", 
            "height": 92, 
            "hier_level": 0, 
            "human_hash": "div_X506_Y1630_W2800_H92", 
            "index": -1, 
            "internal": {
                "elem_dict": {
                    "attributes": {
                        "class": "sqs-block-content"
                    }, 
                    "background-color": "rgba(0, 0, 0, 0)", 
                    "class": "div", 
                    "color": "rgb(255, 255, 255)", 
                    "cssClass": "sqs-block-content", 
                    "domLevel": 12, 
                    "flags": {
                        "checkable": false, 
                        "clickable": false, 
                        "enabled": false, 
                        "focusable": false, 
                        "focused": false, 
                        "scrollable": false
                    }, 
                    "font-family": "ibm-plex-sans", 
                    "font-weight": "400", 
                    "fontSize": 17.6, 
                    "height": 46, 
                    "identifier": "", 
                    "is-focused": false, 
                    "is-hidden": false, 
                    "name": "", 
                    "tagName": "div", 
                    "text": "Benefits for Your Team", 
                    "type": "", 
                    "value": "", 
                    "width": 1400, 
                    "x": 253, 
                    "xPercent": 13.254593175853019, 
                    "y": 815, 
                    "yPercent": 12.66732398197078
                }, 
                "location": {
                    "x": 253, 
                    "y": 815
                }, 
                "size": {
                    "height": 46, 
                    "width": 1400
                }, 
                "tag_name": "div", 
                "text": "Benefits for Your Team"
            }, 
            "is_transformed": true, 
            "package": "", 
            "password": false, 
            "resource-id": "", 
            "scrollable": false, 
            "tag_name": "div", 
            "text": "Benefits for Your Team", 
            "transformed": true, 
            "width": 2800, 
            "x": 506, 
            "y": 1630
        }, 
        {
            "behavior": "", 
            "checkable": false, 
            "class": "div", 
            "clickable": false, 
            "content-desc": "", 
            "enabled": false, 
            "focusable": false, 
            "focused": false, 
            "hash": "+Of5pF5tDRWUvMD1fzV+Eg==\n", 
            "height": 1344, 
            "hier_level": 0, 
            "human_hash": "div_X1904_Y30_W716_H1344", 
            "index": -1, 
            "internal": {
                "elem_dict": {
                    "attributes": {
                        "class": "col sqs-col-3 span-3", 
                        "id": "yui_3_17_2_1_1611600788843_198"
                    }, 
                    "background-color": "rgba(0, 0, 0, 0)", 
                    "class": "div", 
                    "color": "rgb(0, 0, 0)", 
                    "cssClass": "col sqs-col-3 span-3", 
                    "domLevel": 12, 
                    "flags": {
                        "checkable": false, 
                        "clickable": false, 
                        "enabled": false, 
                        "focusable": false, 
                        "focused": false, 
                        "scrollable": false
                    }, 
                    "font-family": "ibm-plex-sans", 
                    "font-weight": "400", 
                    "fontSize": 17.6, 
                    "height": 672, 
                    "identifier": "yui_3_17_2_1_1611600788843_198", 
                    "is-focused": false, 
                    "is-hidden": false, 
                    "name": "", 
                    "tagName": "div", 
                    "text": "<img src=\"https://images.squarespace-cdn.com/content/v1/5fa3332deadd8878ac4cb2cd/1605728212914-RAVUZAKQDFIMUR5GTWLN/ke17ZwdGBToddI8pDm48kOPtmt9kq3Df9ydK2LHH3aVZw-zPPgdn4jUwVcJE1ZvWQUxwkmyExglNqGp0IvTJZUJFbgE-7XRK3dMEBRBhUpxmGopNxzBDum4KUbtWB-MksiSdU5mjAVNjQAW-KQtSPhdWHkdEm-MnflhaMByAPFY/build.png\" alt=\"build.png\" />\n          \n        \n          \n        \n\n        \n      \n        \n      \n\n    \n  \n\n\n  \n\n\nBuildAI-Bots build tests without coding or scripting. Anybody can do it \u2026 get productive fast.\n\n\n\n\n\n\n\n\n  \n\n    \n  \n    \n\n      \n\n      \n        \n          \n        \n        \n\n        \n          \n            \n          \n            <img src=\"https://images.squarespace-cdn.com/content/v1/5fa3332deadd8878ac4cb2cd/1605728189125-ROASF0VGWL1FDL4AR1GN/ke17ZwdGBToddI8pDm48kOPtmt9kq3Df9ydK2LHH3aVZw-zPPgdn4jUwVcJE1ZvWQUxwkmyExglNqGp0IvTJZUJFbgE-7XRK3dMEBRBhUpxmGopNxzBDum4KUbtWB-MksiSdU5mjAVNjQAW-KQtSPhdWHkdEm-MnflhaMByAPFY/scale.png\" alt=\"scale.png\" />\n          \n        \n          \n        \n\n        \n      \n        \n      \n\n    \n  \n\n\n  \n\n\nScaleAI-Bots scale testing to any platform, any app. Create a test for one platform - deploy to many.", 
                    "type": "", 
                    "value": "", 
                    "width": 358, 
                    "x": 952, 
                    "xPercent": 49.998359580052494, 
                    "y": 15, 
                    "yPercent": 0.23167935965184955
                }, 
                "location": {
                    "x": 952, 
                    "y": 15
                }, 
                "size": {
                    "height": 672, 
                    "width": 358
                }, 
                "tag_name": "div", 
                "text": "<img src=\"https://images.squarespace-cdn.com/content/v1/5fa3332deadd8878ac4cb2cd/1605728212914-RAVUZAKQDFIMUR5GTWLN/ke17ZwdGBToddI8pDm48kOPtmt9kq3Df9ydK2LHH3aVZw-zPPgdn4jUwVcJE1ZvWQUxwkmyExglNqGp0IvTJZUJFbgE-7XRK3dMEBRBhUpxmGopNxzBDum4KUbtWB-MksiSdU5mjAVNjQAW-KQtSPhdWHkdEm-MnflhaMByAPFY/build.png\" alt=\"build.png\" />\n          \n        \n          \n        \n\n        \n      \n        \n      \n\n    \n  \n\n\n  \n\n\nBuildAI-Bots build tests without coding or scripting. Anybody can do it \u2026 get productive fast.\n\n\n\n\n\n\n\n\n  \n\n    \n  \n    \n\n      \n\n      \n        \n          \n        \n        \n\n        \n          \n            \n          \n            <img src=\"https://images.squarespace-cdn.com/content/v1/5fa3332deadd8878ac4cb2cd/1605728189125-ROASF0VGWL1FDL4AR1GN/ke17ZwdGBToddI8pDm48kOPtmt9kq3Df9ydK2LHH3aVZw-zPPgdn4jUwVcJE1ZvWQUxwkmyExglNqGp0IvTJZUJFbgE-7XRK3dMEBRBhUpxmGopNxzBDum4KUbtWB-MksiSdU5mjAVNjQAW-KQtSPhdWHkdEm-MnflhaMByAPFY/scale.png\" alt=\"scale.png\" />\n          \n        \n          \n        \n\n        \n      \n        \n      \n\n    \n  \n\n\n  \n\n\nScaleAI-Bots scale testing to any platform, any app. Create a test for one platform - deploy to many."
            }, 
            "is_transformed": true, 
            "package": "", 
            "password": false, 
            "resource-id": "", 
            "scrollable": false, 
            "tag_name": "div", 
            "text": "<img src=\"https://images.squarespace-cdn.com/content/v1/5fa3332deadd8878ac4cb2cd/1605728212914-RAVUZAKQDFIMUR5GTWLN/ke17ZwdGBToddI8pDm48kOPtmt9kq3Df9ydK2LHH3aVZw-zPPgdn4jUwVcJE1ZvWQUxwkmyExglNqGp0IvTJZUJFbgE-7XRK3dMEBRBhUpxmGopNxzBDum4KUbtWB-MksiSdU5mjAVNjQAW-KQtSPhdWHkdEm-MnflhaMByAPFY/build.png\" alt=\"build.png\" />\n          \n        \n          \n        \n\n        \n      \n        \n      \n\n    \n  \n\n\n  \n\n\nBuildAI-Bots build tests without coding or scripting. Anybody can do it \u2026 get productive fast.\n\n\n\n\n\n\n\n\n  \n\n    \n  \n    \n\n      \n\n      \n        \n          \n        \n        \n\n        \n          \n            \n          \n            <img src=\"https://images.squarespace-cdn.com/content/v1/5fa3332deadd8878ac4cb2cd/1605728189125-ROASF0VGWL1FDL4AR1GN/ke17ZwdGBToddI8pDm48kOPtmt9kq3Df9ydK2LHH3aVZw-zPPgdn4jUwVcJE1ZvWQUxwkmyExglNqGp0IvTJZUJFbgE-7XRK3dMEBRBhUpxmGopNxzBDum4KUbtWB-MksiSdU5mjAVNjQAW-KQtSPhdWHkdEm-MnflhaMByAPFY/scale.png\" alt=\"scale.png\" />\n          \n        \n          \n        \n\n        \n      \n        \n      \n\n    \n  \n\n\n  \n\n\nScaleAI-Bots scale testing to any platform, any app. Create a test for one platform - deploy to many.", 
            "transformed": true, 
            "width": 716, 
            "x": 1904, 
            "y": 30
        }, 
        {
            "behavior": "", 
            "checkable": false, 
            "class": "div", 
            "clickable": false, 
            "content-desc": "", 
            "enabled": false, 
            "focusable": false, 
            "focused": false, 
            "hash": "TqmqzFdyGWXbBWociPDuOw==\n", 
            "height": 204, 
            "hier_level": 0, 
            "human_hash": "div_X1938_Y64_W648_H204", 
            "index": -1, 
            "internal": {
                "elem_dict": {
                    "attributes": {
                        "class": "image-block-wrapper has-aspect-ratio preSlide slideIn", 
                        "data-animation-role": "image", 
                        "id": "yui_3_17_2_1_1611600788843_194", 
                        "style": "padding-bottom: 31.4815%; overflow: hidden; transition-timing-function: ease; transition-duration: 0.8s; transition-delay: 0.185567s;"
                    }, 
                    "background-color": "rgba(0, 0, 0, 0)", 
                    "class": "div", 
                    "color": "rgb(0, 0, 0)", 
                    "cssClass": "image-block-wrapper has-aspect-ratio preSlide slideIn", 
                    "domLevel": 17, 
                    "flags": {
                        "checkable": false, 
                        "clickable": false, 
                        "enabled": false, 
                        "focusable": false, 
                        "focused": false, 
                        "scrollable": false
                    }, 
                    "font-family": "ibm-plex-sans", 
                    "font-weight": "400", 
                    "fontSize": 17.6, 
                    "height": 102, 
                    "identifier": "yui_3_17_2_1_1611600788843_194", 
                    "is-focused": false, 
                    "is-hidden": false, 
                    "name": "", 
                    "tagName": "div", 
                    "text": "<img src=\"https://images.squarespace-cdn.com/content/v1/5fa3332deadd8878ac4cb2cd/1605728212914-RAVUZAKQDFIMUR5GTWLN/ke17ZwdGBToddI8pDm48kOPtmt9kq3Df9ydK2LHH3aVZw-zPPgdn4jUwVcJE1ZvWQUxwkmyExglNqGp0IvTJZUJFbgE-7XRK3dMEBRBhUpxmGopNxzBDum4KUbtWB-MksiSdU5mjAVNjQAW-KQtSPhdWHkdEm-MnflhaMByAPFY/build.png\" alt=\"build.png\" />", 
                    "type": "", 
                    "value": "", 
                    "width": 324, 
                    "x": 969, 
                    "xPercent": 50.89074803149606, 
                    "y": 32, 
                    "yPercent": 0.4959006838669568
                }, 
                "location": {
                    "x": 969, 
                    "y": 32
                }, 
                "size": {
                    "height": 102, 
                    "width": 324
                }, 
                "tag_name": "div", 
                "text": "<img src=\"https://images.squarespace-cdn.com/content/v1/5fa3332deadd8878ac4cb2cd/1605728212914-RAVUZAKQDFIMUR5GTWLN/ke17ZwdGBToddI8pDm48kOPtmt9kq3Df9ydK2LHH3aVZw-zPPgdn4jUwVcJE1ZvWQUxwkmyExglNqGp0IvTJZUJFbgE-7XRK3dMEBRBhUpxmGopNxzBDum4KUbtWB-MksiSdU5mjAVNjQAW-KQtSPhdWHkdEm-MnflhaMByAPFY/build.png\" alt=\"build.png\" />"
            }, 
            "is_transformed": true, 
            "package": "", 
            "password": false, 
            "resource-id": "", 
            "scrollable": false, 
            "tag_name": "div", 
            "text": "<img src=\"https://images.squarespace-cdn.com/content/v1/5fa3332deadd8878ac4cb2cd/1605728212914-RAVUZAKQDFIMUR5GTWLN/ke17ZwdGBToddI8pDm48kOPtmt9kq3Df9ydK2LHH3aVZw-zPPgdn4jUwVcJE1ZvWQUxwkmyExglNqGp0IvTJZUJFbgE-7XRK3dMEBRBhUpxmGopNxzBDum4KUbtWB-MksiSdU5mjAVNjQAW-KQtSPhdWHkdEm-MnflhaMByAPFY/build.png\" alt=\"build.png\" />", 
            "transformed": true, 
            "width": 648, 
            "x": 1938, 
            "y": 64
        }, 
        {
            "behavior": "", 
            "checkable": false, 
            "class": "div", 
            "clickable": false, 
            "content-desc": "", 
            "enabled": false, 
            "focusable": false, 
            "focused": false, 
            "hash": "qIzNFN4ycQNvaUtmvkWIoQ==\n", 
            "height": 68, 
            "hier_level": 0, 
            "human_hash": "div_X1460_Y64_W410_H68", 
            "index": -1, 
            "internal": {
                "elem_dict": {
                    "attributes": {
                        "class": "sqs-block-content"
                    }, 
                    "background-color": "rgba(0, 0, 0, 0)", 
                    "class": "div", 
                    "color": "rgb(0, 0, 0)", 
                    "cssClass": "sqs-block-content", 
                    "domLevel": 14, 
                    "flags": {
                        "checkable": false, 
                        "clickable": false, 
                        "enabled": false, 
                        "focusable": false, 
                        "focused": false, 
                        "scrollable": false
                    }, 
                    "font-family": "ibm-plex-sans", 
                    "font-weight": "400", 
                    "fontSize": 17.6, 
                    "height": 34, 
                    "identifier": "", 
                    "is-focused": false, 
                    "is-hidden": false, 
                    "name": "", 
                    "tagName": "div", 
                    "text": "", 
                    "type": "", 
                    "value": "", 
                    "width": 205, 
                    "x": 730, 
                    "xPercent": 38.34563648293963, 
                    "y": 32, 
                    "yPercent": 0.4959006838669568
                }, 
                "location": {
                    "x": 730, 
                    "y": 32
                }, 
                "size": {
                    "height": 34, 
                    "width": 205
                }, 
                "tag_name": "div", 
                "text": ""
            }, 
            "is_transformed": true, 
            "package": "", 
            "password": false, 
            "resource-id": "", 
            "scrollable": false, 
            "tag_name": "div", 
            "text": "", 
            "transformed": true, 
            "width": 410, 
            "x": 1460, 
            "y": 64
        }, 
        {
            "behavior": "", 
            "checkable": false, 
            "class": "div", 
            "clickable": false, 
            "content-desc": "", 
            "enabled": false, 
            "focusable": false, 
            "focused": false, 
            "hash": "LDbjN6aJQrVYs3NL4LRAdg==\n", 
            "height": 232, 
            "hier_level": 0, 
            "human_hash": "div_X1938_Y722_W648_H232", 
            "index": -1, 
            "internal": {
                "elem_dict": {
                    "attributes": {
                        "class": "image-block-wrapper has-aspect-ratio preSlide slideIn", 
                        "data-animation-role": "image", 
                        "id": "yui_3_17_2_1_1611600788843_218", 
                        "style": "padding-bottom: 35.7143%; overflow: hidden; transition-timing-function: ease; transition-duration: 0.8s; transition-delay: 0.204124s;"
                    }, 
                    "background-color": "rgba(0, 0, 0, 0)", 
                    "class": "div", 
                    "color": "rgb(0, 0, 0)", 
                    "cssClass": "image-block-wrapper has-aspect-ratio preSlide slideIn", 
                    "domLevel": 17, 
                    "flags": {
                        "checkable": false, 
                        "clickable": false, 
                        "enabled": false, 
                        "focusable": false, 
                        "focused": false, 
                        "scrollable": false
                    }, 
                    "font-family": "ibm-plex-sans", 
                    "font-weight": "400", 
                    "fontSize": 17.6, 
                    "height": 116, 
                    "identifier": "yui_3_17_2_1_1611600788843_218", 
                    "is-focused": false, 
                    "is-hidden": false, 
                    "name": "", 
                    "tagName": "div", 
                    "text": "<img src=\"https://images.squarespace-cdn.com/content/v1/5fa3332deadd8878ac4cb2cd/1605728189125-ROASF0VGWL1FDL4AR1GN/ke17ZwdGBToddI8pDm48kOPtmt9kq3Df9ydK2LHH3aVZw-zPPgdn4jUwVcJE1ZvWQUxwkmyExglNqGp0IvTJZUJFbgE-7XRK3dMEBRBhUpxmGopNxzBDum4KUbtWB-MksiSdU5mjAVNjQAW-KQtSPhdWHkdEm-MnflhaMByAPFY/scale.png\" alt=\"scale.png\" />", 
                    "type": "", 
                    "value": "", 
                    "width": 324, 
                    "x": 969, 
                    "xPercent": 50.89074803149606, 
                    "y": 361, 
                    "yPercent": 5.61154608330743
                }, 
                "location": {
                    "x": 969, 
                    "y": 361
                }, 
                "size": {
                    "height": 116, 
                    "width": 324
                }, 
                "tag_name": "div", 
                "text": "<img src=\"https://images.squarespace-cdn.com/content/v1/5fa3332deadd8878ac4cb2cd/1605728189125-ROASF0VGWL1FDL4AR1GN/ke17ZwdGBToddI8pDm48kOPtmt9kq3Df9ydK2LHH3aVZw-zPPgdn4jUwVcJE1ZvWQUxwkmyExglNqGp0IvTJZUJFbgE-7XRK3dMEBRBhUpxmGopNxzBDum4KUbtWB-MksiSdU5mjAVNjQAW-KQtSPhdWHkdEm-MnflhaMByAPFY/scale.png\" alt=\"scale.png\" />"
            }, 
            "is_transformed": true, 
            "package": "", 
            "password": false, 
            "resource-id": "", 
            "scrollable": false, 
            "tag_name": "div", 
            "text": "<img src=\"https://images.squarespace-cdn.com/content/v1/5fa3332deadd8878ac4cb2cd/1605728189125-ROASF0VGWL1FDL4AR1GN/ke17ZwdGBToddI8pDm48kOPtmt9kq3Df9ydK2LHH3aVZw-zPPgdn4jUwVcJE1ZvWQUxwkmyExglNqGp0IvTJZUJFbgE-7XRK3dMEBRBhUpxmGopNxzBDum4KUbtWB-MksiSdU5mjAVNjQAW-KQtSPhdWHkdEm-MnflhaMByAPFY/scale.png\" alt=\"scale.png\" />", 
            "transformed": true, 
            "width": 648, 
            "x": 1938, 
            "y": 722
        }, 
        {
            "behavior": "", 
            "checkable": false, 
            "class": "div", 
            "clickable": false, 
            "content-desc": "", 
            "enabled": false, 
            "focusable": false, 
            "focused": false, 
            "hash": "pvxenJhlqaZJXdRWEh7xWA==\n", 
            "height": 448, 
            "hier_level": 0, 
            "human_hash": "div_X2622_Y964_W718_H448", 
            "index": -1, 
            "internal": {
                "elem_dict": {
                    "attributes": {
                        "class": "sqs-block html-block sqs-block-html", 
                        "data-block-type": "2", 
                        "id": "block-yui_3_17_2_1_1605635471495_377067"
                    }, 
                    "background-color": "rgba(0, 0, 0, 0)", 
                    "class": "div", 
                    "color": "rgb(0, 0, 0)", 
                    "cssClass": "sqs-block html-block sqs-block-html", 
                    "domLevel": 11, 
                    "flags": {
                        "checkable": false, 
                        "clickable": false, 
                        "enabled": false, 
                        "focusable": false, 
                        "focused": false, 
                        "scrollable": false
                    }, 
                    "font-family": "ibm-plex-sans", 
                    "font-weight": "400", 
                    "fontSize": 17.6, 
                    "height": 224, 
                    "identifier": "block-yui_3_17_2_1_1605635471495_377067", 
                    "is-focused": false, 
                    "is-hidden": false, 
                    "name": "", 
                    "tagName": "div", 
                    "text": "MaintainAI-Bots maintain tests automatically... improve quality everywhere. Keep testing running to meet critical business deadlines", 
                    "type": "", 
                    "value": "", 
                    "width": 359, 
                    "x": 1311, 
                    "xPercent": 68.81889763779527, 
                    "y": 482, 
                    "yPercent": 7.484894700031084
                }, 
                "location": {
                    "x": 1311, 
                    "y": 482
                }, 
                "size": {
                    "height": 224, 
                    "width": 359
                }, 
                "tag_name": "div", 
                "text": "MaintainAI-Bots maintain tests automatically... improve quality everywhere. Keep testing running to meet critical business deadlines"
            }, 
            "is_transformed": true, 
            "package": "", 
            "password": false, 
            "resource-id": "", 
            "scrollable": false, 
            "tag_name": "div", 
            "text": "MaintainAI-Bots maintain tests automatically... improve quality everywhere. Keep testing running to meet critical business deadlines", 
            "transformed": true, 
            "width": 718, 
            "x": 2622, 
            "y": 964
        }
    ], 
    "cpu": 0, 
    "jank": 0, 
    "mem": 0, 
    "net": 0, 
    "processed": false, 
    "timing": 0
}